resotocore/__init__.py
resotocore/__main__.py
resotocore/async_extensions.py
resotocore/compat.py
resotocore/console_renderer.py
resotocore/constants.py
resotocore/core_config.py
resotocore/dependencies.py
resotocore/error.py
resotocore/ids.py
resotocore/message_bus.py
resotocore/metrics.py
resotocore/service.py
resotocore/system_start.py
resotocore/types.py
resotocore/util.py
resotocore/validator.py
resotocore/worker_task_queue.py
resotocore/action_handlers/__init__.py
resotocore/action_handlers/merge_outer_edge_handler.py
resotocore/analytics/__init__.py
resotocore/analytics/posthog.py
resotocore/analytics/recurrent_events.py
resotocore/cli/__init__.py
resotocore/cli/cli.py
resotocore/cli/command.py
resotocore/cli/model.py
resotocore/cli/tip_of_the_day.py
resotocore/config/__init__.py
resotocore/config/config_handler_service.py
resotocore/config/config_override_service.py
resotocore/config/core_config_handler.py
resotocore/db/__init__.py
resotocore/db/arango_query.py
resotocore/db/arangodb_extensions.py
resotocore/db/arangodb_functions.py
resotocore/db/async_arangodb.py
resotocore/db/configdb.py
resotocore/db/db_access.py
resotocore/db/deferredouteredgedb.py
resotocore/db/entitydb.py
resotocore/db/graphdb.py
resotocore/db/jobdb.py
resotocore/db/model.py
resotocore/db/modeldb.py
resotocore/db/packagedb.py
resotocore/db/reportdb.py
resotocore/db/runningtaskdb.py
resotocore/db/system_data_db.py
resotocore/db/templatedb.py
resotocore/db/timeseriesdb.py
resotocore/db/usagedb.py
resotocore/graph_manager/__init__.py
resotocore/graph_manager/graph_manager.py
resotocore/infra_apps/__init__.py
resotocore/infra_apps/local_runtime.py
resotocore/infra_apps/manifest.py
resotocore/infra_apps/package_manager.py
resotocore/infra_apps/runtime.py
resotocore/jupyterlite/bootstrap.js
resotocore/jupyterlite/config-utils.js
resotocore/jupyterlite/icon-120x120.png
resotocore/jupyterlite/icon-512x512.png
resotocore/jupyterlite/index.html
resotocore/jupyterlite/jupyter-lite.ipynb
resotocore-3.9.0.dist-info/METADATA
resotocore-3.9.0.dist-info/WHEEL
resotocore-3.9.0.dist-info/entry_points.txt
resotocore-3.9.0.dist-info/top_level.txt
resotocore-3.9.0.dist-info/RECORD
