Metadata-Version: 2.1
Name: resotocore
Version: 3.9.0
Summary: Keeps all the things.
Author: Some Engineering Inc.
License: AGPLv3
Project-URL: Homepage, https://resoto.com
Classifier: Development Status :: 5 - Production/Stable
Classifier: Intended Audience :: System Administrators
Classifier: Intended Audience :: Information Technology
Classifier: License :: OSI Approved :: GNU Affero General Public License v3 or later (AGPLv3+)
Classifier: Programming Language :: Python :: 3.9
Classifier: Operating System :: POSIX :: Linux
Classifier: Operating System :: Unix
Classifier: Environment :: Console
Classifier: Natural Language :: English
Classifier: Topic :: Security
Classifier: Topic :: Utilities
Requires-Python: >=3.9
Requires-Dist: APScheduler
Requires-Dist: Cerberus
Requires-Dist: Jinja2
Requires-Dist: aiofiles
Requires-Dist: aiohttp-jinja2
Requires-Dist: aiohttp-swagger3
Requires-Dist: aiohttp[speedups]
Requires-Dist: aiostream
Requires-Dist: cryptography
Requires-Dist: deepdiff
Requires-Dist: detect-secrets
Requires-Dist: frozendict
Requires-Dist: jq
Requires-Dist: jsons
Requires-Dist: parsy
Requires-Dist: plantuml
Requires-Dist: posthog
Requires-Dist: python-arango
Requires-Dist: python-dateutil
Requires-Dist: resotodatalink >=1.2.0
Requires-Dist: resotoui
Requires-Dist: rich
Requires-Dist: toolz
Requires-Dist: transitions
Requires-Dist: tzlocal
Requires-Dist: ustache
Provides-Extra: extra
Requires-Dist: resotodatalink[extra] ; extra == 'extra'
Provides-Extra: test
Requires-Dist: black ; extra == 'test'
Requires-Dist: coverage ; extra == 'test'
Requires-Dist: flake8 ; extra == 'test'
Requires-Dist: hypothesis ; extra == 'test'
Requires-Dist: mypy ; extra == 'test'
Requires-Dist: pep8-naming ; extra == 'test'
Requires-Dist: pip-tools ; extra == 'test'
Requires-Dist: pylint ; extra == 'test'
Requires-Dist: pytest ; extra == 'test'
Requires-Dist: pytest-asyncio ; extra == 'test'
Requires-Dist: pytest-cov ; extra == 'test'
Requires-Dist: resotoclient >=1.5.0 ; extra == 'test'
Requires-Dist: toml ; extra == 'test'
Requires-Dist: tox ; extra == 'test'
Requires-Dist: types-aiofiles ; extra == 'test'
